TypedClass/__init__.py
TypedClass/index.py
TypedClass-0.0.5.dist-info/LICENSE
TypedClass-0.0.5.dist-info/METADATA
TypedClass-0.0.5.dist-info/WHEEL
TypedClass-0.0.5.dist-info/top_level.txt
TypedClass-0.0.5.dist-info/RECORD
