Metadata-Version: 2.1
Name: TypedClass
Version: 0.0.5
Summary: Extend other classes to give them type checking via annotations
Home-page: https://github.com/w0251251/TypedClass
Author: Nicholas Tancredi
Author-email: nicholastancredi@gmail.com
License: GNU
Platform: UNKNOWN
